version_filter/__init__.py
version_filter/version_filter.py
version_filter-0.7.3.dist-info/DESCRIPTION.rst
version_filter-0.7.3.dist-info/METADATA
version_filter-0.7.3.dist-info/RECORD
version_filter-0.7.3.dist-info/WHEEL
version_filter-0.7.3.dist-info/metadata.json
version_filter-0.7.3.dist-info/top_level.txt
