Metadata-Version: 2.0
Name: version-filter
Version: 0.7.3
Summary: A semantic and regex version filtering/masking library.
Home-page: https://github.com/dropseedlabs/version-filter
Author: Dropseed
Author-email: python@dropseed.io
License: MIT license
Keywords: version_filter
Platform: UNKNOWN
Classifier: Development Status :: 2 - Pre-Alpha
Classifier: Intended Audience :: Developers
Classifier: License :: OSI Approved :: MIT License
Classifier: Natural Language :: English
Classifier: Programming Language :: Python :: 2
Classifier: Programming Language :: Python :: 2.7
Classifier: Programming Language :: Python :: 3
Classifier: Programming Language :: Python :: 3.3
Classifier: Programming Language :: Python :: 3.4
Classifier: Programming Language :: Python :: 3.5
Classifier: Programming Language :: Python :: 3.6
Requires-Dist: semantic-version (==2.6.0)
